<?xml version="1.0" encoding="utf-8"?>
<Defs>
  <FactionDef ParentName="PlayerFactionBase">
    <defName>LightRabbitPlayerFaction</defName>
    <label>辉明兔</label>
    <description>一群从辉明王朝脱离出来的兔子，似乎是为什么目的而行进着。</description>
    <isPlayer>true</isPlayer>
    <basicMemberKind>LightRabbitColonist</basicMemberKind>
    <pawnSingular>辉明兔</pawnSingular>
    <pawnsPlural>辉明兔</pawnsPlural>
    <factionIconPath>UI/Ideology/GloryElveDynastyWhite</factionIconPath>
    <factionNameMaker>NamerFactionGloryElveDynasty</factionNameMaker>
    <settlementNameMaker>NamerSettlementGloryElveDynasty</settlementNameMaker>
    <techLevel>Industrial</techLevel>
    <colorSpectrum Inherit="False">
      <li>(255, 255, 0)</li>
    </colorSpectrum>
    <backstoryFilters>
      <li>
        <categories>
          <li>LightRabbit</li>
        </categories>
      </li>
    </backstoryFilters>
    <geneticVariance>1</geneticVariance>
    <startingResearchTags>
      <li>ClassicStart</li>
    </startingResearchTags>
    <startingTechprintsResearchTags>
      <li>ClassicStart</li>
      <li>ClassicStartTechprints</li>
    </startingTechprintsResearchTags>
    <apparelStuffFilter>
      <thingDefs>
        <li>Cloth</li>
      </thingDefs>
    </apparelStuffFilter>
    <allowedCultures>
      <li>GloryElveDynasty</li>
    </allowedCultures>
    <structureMemeWeights>
      <Structure_GloryElveDynasty MayRequire="Ludeon.RimWorld.Ideology">1</Structure_GloryElveDynasty>
    </structureMemeWeights>
    <requiredMemes>
      <li MayRequire="Ludeon.RimWorld.Ideology">Structure_GloryElveDynasty</li>
      <li MayRequire="Ludeon.RimWorld.Ideology">GloryElveDynastyMeme</li>
    </requiredMemes>
    <allowedMemes>
      <li MayRequire="Ludeon.RimWorld.Ideology">Structure_GloryElveDynasty</li>
      <li MayRequire="Ludeon.RimWorld.Ideology">GloryElveDynastyMeme</li>
    </allowedMemes>
  </FactionDef>
</Defs>